vs-code-designing/Sequential Systems/D-FF-posedge-clk-synchronous-posedge-reset/design.v
module designn (
    clk,d,rst,q
);
    input clk,d,rst;
    output reg q;
    /* in case of synchronous 
    circuit reset signal will 
    have effect only when there
     is positive triggered in the
      global clock signal.
      */

    always @(posedge clk) begin
        if (rst) 
            q <=1'd0;
        else
            q<=d;
    end
endmodule

vs-code-designing/Sequential Systems/D-FF-posedge-clk-synchronous-posedge-reset/design-test.v
module testbench (
    
);
    reg clk,d,rst;
    wire q;

    designn DUT(clk,d,rst,q);

    
    initial begin
        $dumpfile("designn.vcd");
        $dumpvars(0,testbench);
        rst=0;
        d=0;clk=0;#20;
        d=1;clk=0;#10;
        d=1;clk=1;#10;
        rst=1;
        d=0;clk=1;#10;
        d=0;clk=0;#10;
        d=1;clk=0;#20;
        d=1;clk=0;#10;
        d=0;clk=1;#10;
        d=1;clk=1;#10;
        d=1;clk=0;#10;
        d=0;clk=0;#20;
        $finish;
        $display("compilled successfully");
    end
endmodule

vs-code-designing/Sequential Systems/D-FF-posedge-clk-synchronous-posedge-reset/designn.vcd
$date
	Mon Jun 06 21:31:52 2022
$end
$version
	Icarus Verilog
$end
$timescale
	1s
$end
$scope module testbench $end
$var wire 1 ! q $end
$var reg 1 " clk $end
$var reg 1 # d $end
$var reg 1 $ rst $end
$scope module DUT $end
$var wire 1 " clk $end
$var wire 1 # d $end
$var wire 1 $ rst $end
$var reg 1 ! q $end
$upscope $end
$upscope $end
$enddefinitions $end
#0
$dumpvars
0$
0#
0"
x!
$end
#20
1#
#30
1!
1"
#40
0#
1$
#50
0"
#60
1#
#90
0!
1"
0#
#100
1#
#110
0"
#120
0#
