vs-code-designing/Sequential Systems/D-latch-async-reset/d_la_a_r.v
module dlat (
    en,d,q,rst
);
    input en,d,rst;
    output reg q;

    always @(en,d,rst) begin
        if(rst)
            q=1'b0;
        else if (en) 
            q=d;
        
    end
endmodule

vs-code-designing/Sequential Systems/D-latch-async-reset/d_la_a_r-test.v
module testbench (
    
);
    reg en,d,rst;
    wire q;

    dlat DUT(en,d,q,rst);

    initial begin
        $dumpfile("dlat.vcd");
        $dumpvars(0,testbench);
    // normal systems can be viewed just by commenting out reset signal

        rst=0;
        en=1;d=0;#5;
        en=1;d=1;#15;
        en=0;d=1;#5;
        en=0;d=0;#15;
        rst=1;
        en=1;d=0;#5;
        en=1;d=1;#15;
        en=0;d=1;#5;
        en=0;d=0;#15;
        en=1;d=0;#20;

        $finish;
        $display("compilled successfullly");
        

    end
endmodule

vs-code-designing/Sequential Systems/D-latch-async-reset/dlat.vcd
$date
	Mon Jun 06 20:06:24 2022
$end
$version
	Icarus Verilog
$end
$timescale
	1s
$end
$scope module testbench $end
$var wire 1 ! q $end
$var reg 1 " d $end
$var reg 1 # en $end
$var reg 1 $ rst $end
$scope module DUT $end
$var wire 1 " d $end
$var wire 1 # en $end
$var wire 1 $ rst $end
$var reg 1 ! q $end
$upscope $end
$upscope $end
$enddefinitions $end
#0
$dumpvars
0$
1#
0"
0!
$end
#5
1!
1"
#20
0#
#25
0"
#40
0!
1#
1$
#45
1"
#60
0#
#65
0"
#80
1#
