vs-code-designing/large schematic check/design.v
 module designn (
     A,B,C,D,E,F,Y
 );
    input A,B,C,D,E,F;
    output Y;
    wire T1,T2,T3,T4,T5,T6;

    and #1 g1(T1,A,B);
    or #1 g2(T2,C,D);
    nand #1 g3(T3,E,F);
    xor #1 g4(T4,T1,T2);
    not #1 g5(T5,T3);
    nor #1 g6(T6,T4,T5);
    not #1 g7(Y,T6);
 endmodule

vs-code-designing/Combinational Systems/large schematic check/design-test.v
module testbench (
    
);
    reg A,B,C,D,E,F;
    wire Y;

    designn DUT(A,B,C,D,E,F,Y);

    initial begin
        $monitor($time," a=%b, b=%b, c=%b, d=%b, e=%b, f=%b, y=%b",A,B,C,D,E,F,Y);
        $dumpfile("design.vcd");
        $dumpvars(0,testbench);

        #5 A=0;B=0;C=0;D=0;E=0;F=0;
        #5 A=1;B=1;F=1;
        #5 E=1;
        #5 $finish;
        $display("compilled successfully");

    end

endmodule

vs-code-designing/Combinational Systems/large schematic check/design.vcd
$date
	Fri Jun 03 11:42:52 2022
$end
$version
	Icarus Verilog
$end
$timescale
	1s
$end
$scope module testbench $end
$var wire 1 ! Y $end
$var reg 1 " A $end
$var reg 1 # B $end
$var reg 1 $ C $end
$var reg 1 % D $end
$var reg 1 & E $end
$var reg 1 ' F $end
$scope module DUT $end
$var wire 1 " A $end
$var wire 1 # B $end
$var wire 1 $ C $end
$var wire 1 % D $end
$var wire 1 & E $end
$var wire 1 ' F $end
$var wire 1 ( T1 $end
$var wire 1 ) T2 $end
$var wire 1 * T3 $end
$var wire 1 + T4 $end
$var wire 1 , T5 $end
$var wire 1 - T6 $end
$var wire 1 ! Y $end
$upscope $end
$upscope $end
$enddefinitions $end
#0
$dumpvars
x-
x,
x+
x*
x)
x(
x'
x&
x%
x$
x#
x"
x!
$end
#5
0'
0&
0%
0$
0#
0"
#6
1*
0)
0(
#7
0,
0+
#8
1-
#9
0!
#10
1'
1#
1"
#11
1(
#12
1+
#13
0-
#14
1!
#15
1&
#16
0*
#17
1,
