practice/revision-verilog/design.v
// sync d flip flop with positive triggered clock
module sdff (
    clk,rst,d,q
);
    input clk,rst,d;
    output reg q;

    always @(posedge clk) begin
        if(rst)
            q=1'b0;
        else
            q=d; 
    end
endmodule

practice/revision-verilog/design-test.v
module testbench (
    
);
    reg clk,rst,d;
    wire q;

    sdff DUT(clk,rst,d,q);

    initial
    clk=0;
    always #10 clk= ~clk;

    initial begin
        $dumpfile("sdff.vcd");
        $dumpvars(0,testbench);
        rst=0;
        d=0; #12;
        d=1; #20;
        d=0; #17;
        d=1; #12;
        rst=1; #20;
        rst=0; #20;
        $finish;
    end
endmodule

practice/revision-verilog/sdff.vcd
$date
	Sat Aug 06 20:02:33 2022
$end
$version
	Icarus Verilog
$end
$timescale
	1s
$end
$scope module testbench $end
$var wire 1 ! q $end
$var reg 1 " clk $end
$var reg 1 # d $end
$var reg 1 $ rst $end
$scope module DUT $end
$var wire 1 " clk $end
$var wire 1 # d $end
$var wire 1 $ rst $end
$var reg 1 ! q $end
$upscope $end
$upscope $end
$enddefinitions $end
#0
$dumpvars
0$
0#
0"
x!
$end
#10
0!
1"
#12
1#
#20
0"
#30
1!
1"
#32
0#
#40
0"
#49
1#
#50
1"
#60
0"
#61
1$
#70
0!
1"
#80
0"
#81
0$
#90
1!
1"
