vs-code-designing/mux-design-schematic/mux.v
module mux41 (
    s0,s1,i0,i1,i2,i3,y
);
    input s0,s1;
    input i0,i1,i2,i3;
    output y;
    wire t1,t2,t3,t4,t5,t6;

    not #1 g1(t1,s0);
    not #1 g2(t2,s1);
    and #1 g3(t3,t1,t2,i0);
    and #1 g4(t4,t1,s1,i1);
    and #1 g5(t5,s0,t2,i2);
    and #1 g6(t6,s0,s1,i3);
    or #1 g7(y,t3,t4,t5,t6);

endmodule

vs-code-designing/mux-design/mux-test.v
module testbench (
    
);
    reg s0,s1,i0,i1,i2,i3;
    wire y;
    mux41 DUT(s0,s1,i0,i1,i2,i3,y);

    initial begin
        $monitor($time," s0=%b, s1=%b, i0=%b, i1=%b, i2=%b, i3=%b, y=%b",s0,s1,i0,i1,i2,i3,y);

        $dumpfile("mux41.vcd");
        $dumpvars(0,testbench);

        #5 s0=0;s1=0;i0=1;i1=0;i2=0;i3=1;
        #5 s0=1;s1=0;
        #5 s0=0;s1=1;
        #5 s0=1;s1=1;
        #5 $finish;
        $display("compilled successfully");

    end

endmodule

vs-code-designing/Combinational Systems/mux-design-schematic/mux41.vcd
$date
	Sat Jun 04 16:50:48 2022
$end
$version
	Icarus Verilog
$end
$timescale
	1s
$end
$scope module testbench $end
$var wire 1 ! y $end
$var reg 1 " i0 $end
$var reg 1 # i1 $end
$var reg 1 $ i2 $end
$var reg 1 % i3 $end
$var reg 1 & s0 $end
$var reg 1 ' s1 $end
$scope module DUT $end
$var wire 1 " i0 $end
$var wire 1 # i1 $end
$var wire 1 $ i2 $end
$var wire 1 % i3 $end
$var wire 1 & s0 $end
$var wire 1 ' s1 $end
$var wire 1 ( t1 $end
$var wire 1 ) t2 $end
$var wire 1 * t3 $end
$var wire 1 + t4 $end
$var wire 1 , t5 $end
$var wire 1 - t6 $end
$var wire 1 ! y $end
$upscope $end
$upscope $end
$enddefinitions $end
#0
$dumpvars
x-
x,
x+
x*
x)
x(
x'
x&
x%
x$
x#
x"
x!
$end
#5
1%
0$
0#
1"
0'
0&
#6
1)
0+
1(
0,
0-
#7
1*
#8
1!
#10
1&
#11
0(
#12
0*
#13
0!
#15
1'
0&
#16
0)
1(
#20
1&
#21
0(
1-
#22
1!
